poplar_logging/__init__.py
poplar_logging/logger.py
poplar_logging-1.2.3.dist-info/LICENSE
poplar_logging-1.2.3.dist-info/METADATA
poplar_logging-1.2.3.dist-info/WHEEL
poplar_logging-1.2.3.dist-info/top_level.txt
poplar_logging-1.2.3.dist-info/RECORD
