Metadata-Version: 2.1
Name: poplar_logging
Version: 1.2.3
Summary: Simple Python logging library
Author-email: Odai Athamneh <heyodai@gmail.com>
Project-URL: Homepage, https://github.com/heyodai/poplar
Classifier: Programming Language :: Python :: 3
Classifier: License :: OSI Approved :: MIT License
Classifier: Operating System :: OS Independent
Requires-Python: >=3.7
License-File: LICENSE
